{
    "configurations": [
        {
            "name": "Linux",
            "includePath": [
                "${workspaceFolder}/**",
                "/usr/include",
                "/usr/include/**",
                "/usr/lib/llvm-11/lib/clang/11.0.0/include/",
                "/usr/lib/llvm-10/lib/clang/10.0.0/include/",
                "/opt/otf2/include/"
            ],
            "defines": [],
            "compilerPath": "/usr/bin/clang",
            "cStandard": "gnu17",
            "cppStandard": "gnu++14",
            "intelliSenseMode": "linux-gcc-x86"
        }
    ],
    "version": 4
}